{
    "scene_name": "Scene",
    "objects": {
        "Light": {
            "name": "Light",
            "type": "LIGHT",
            "visible": true,
            "location": {
                "x": 4.076245307922363,
                "y": 1.0054539442062378,
                "z": 5.903861999511719
            },
            "rotation_euler": {
                "x": 0.6503279805183411,
                "y": 0.055217113345861435,
                "z": 1.8663908243179321
            },
            "scale": {
                "x": 1.0,
                "y": 1.0,
                "z": 1.0
            },
            "dimensions": {
                "x": 0.0,
                "y": 0.0,
                "z": 0.0
            },
            "bound_box": [
                [
                    0.0,
                    0.0,
                    0.0
                ],
                [
                    0.0,
                    0.0,
                    0.0
                ],
                [
                    0.0,
                    0.0,
                    0.0
                ],
                [
                    0.0,
                    0.0,
                    0.0
                ],
                [
                    0.0,
                    0.0,
                    0.0
                ],
                [
                    0.0,
                    0.0,
                    0.0
                ],
                [
                    0.0,
                    0.0,
                    0.0
                ],
                [
                    0.0,
                    0.0,
                    0.0
                ]
            ],
            "matrix_world": [
                [
                    -0.29086464643478394,
                    -0.7711008191108704,
                    0.5663931965827942,
                    4.076245307922363
                ],
                [
                    0.9551711678504944,
                    -0.1998833566904068,
                    0.21839119493961334,
                    1.0054539442062378
                ],
                [
                    -0.05518905818462372,
                    0.6045247316360474,
                    0.7946722507476807,
                    5.903861999511719
                ],
                [
                    0.0,
                    0.0,
                    0.0,
                    1.0
                ]
            ]
        },
        "Camera": {
            "name": "Camera",
            "type": "CAMERA",
            "visible": true,
            "location": {
                "x": -17.778900146484375,
                "y": -21.35580062866211,
                "z": 22.988300323486328
            },
            "rotation_euler": {
                "x": 0.8998792171478271,
                "y": -3.725290298461914e-09,
                "z": -1.0418219566345215
            },
            "scale": {
                "x": 1.0,
                "y": 1.0,
                "z": 1.0
            },
            "dimensions": {
                "x": 0.0,
                "y": 0.0,
                "z": 0.0
            },
            "bound_box": [
                [
                    0.0,
                    0.0,
                    0.0
                ],
                [
                    0.0,
                    0.0,
                    0.0
                ],
                [
                    0.0,
                    0.0,
                    0.0
                ],
                [
                    0.0,
                    0.0,
                    0.0
                ],
                [
                    0.0,
                    0.0,
                    0.0
                ],
                [
                    0.0,
                    0.0,
                    0.0
                ],
                [
                    0.0,
                    0.0,
                    0.0
                ],
                [
                    0.0,
                    0.0,
                    0.0
                ]
            ],
            "matrix_world": [
                [
                    0.5046481490135193,
                    0.5367331504821777,
                    -0.6762009859085083,
                    -17.778900146484375
                ],
                [
                    -0.8633251190185547,
                    0.313742071390152,
                    -0.395266592502594,
                    -21.35580062866211
                ],
                [
                    3.725290298461914e-09,
                    0.7832518219947815,
                    0.6217045783996582,
                    22.988300323486328
                ],
                [
                    0.0,
                    0.0,
                    0.0,
                    1.0
                ]
            ]
        },
        "desk1": {
            "name": "desk1",
            "type": "MESH",
            "visible": true,
            "location": {
                "x": 0.0,
                "y": 0.0,
                "z": 0.0
            },
            "rotation_euler": {
                "x": 1.570796251296997,
                "y": 0.0,
                "z": 1.5707963705062866
            },
            "scale": {
                "x": 1.0,
                "y": 1.0,
                "z": 1.0
            },
            "dimensions": {
                "x": 4.038548946380615,
                "y": 3.9874911308288574,
                "z": 9.503341674804688
            },
            "bound_box": [
                [
                    -0.47810301184654236,
                    0.05196800082921982,
                    -4.137495994567871
                ],
                [
                    -0.47810301184654236,
                    0.05196800082921982,
                    5.365845203399658
                ],
                [
                    -0.47810301184654236,
                    4.039459228515625,
                    5.365845203399658
                ],
                [
                    -0.47810301184654236,
                    4.039459228515625,
                    -4.137495994567871
                ],
                [
                    3.56044602394104,
                    0.05196800082921982,
                    -4.137495994567871
                ],
                [
                    3.56044602394104,
                    0.05196800082921982,
                    5.365845203399658
                ],
                [
                    3.56044602394104,
                    4.039459228515625,
                    5.365845203399658
                ],
                [
                    3.56044602394104,
                    4.039459228515625,
                    -4.137495994567871
                ]
            ],
            "matrix_world": [
                [
                    -4.371138828673793e-08,
                    -7.549790126404332e-08,
                    1.0,
                    0.0
                ],
                [
                    1.0,
                    -3.3001180777756647e-15,
                    4.371138828673793e-08,
                    0.0
                ],
                [
                    0.0,
                    1.0,
                    7.549790126404332e-08,
                    0.0
                ],
                [
                    0.0,
                    0.0,
                    0.0,
                    1.0
                ]
            ],
            "vertex_count": 3827,
            "polygon_count": 3716,
            "material_count": 1
        },
        "keyboard1": {
            "name": "keyboard1",
            "type": "MESH",
            "visible": true,
            "location": {
                "x": 1.5,
                "y": 0.4999998211860657,
                "z": 4.099999904632568
            },
            "rotation_euler": {
                "x": 0.0,
                "y": -0.0,
                "z": 0.0
            },
            "scale": {
                "x": 0.05999999865889549,
                "y": 0.05999999865889549,
                "z": 0.05999999865889549
            },
            "dimensions": {
                "x": 2.9757118225097656,
                "y": 1.400459885597229,
                "z": 0.11670000106096268
            },
            "bound_box": [
                [
                    -24.768400192260742,
                    -11.700200080871582,
                    0.000699999975040555
                ],
                [
                    -24.768400192260742,
                    -11.700200080871582,
                    1.9457000494003296
                ],
                [
                    -24.768400192260742,
                    11.640800476074219,
                    1.9457000494003296
                ],
                [
                    -24.768400192260742,
                    11.640800476074219,
                    0.000699999975040555
                ],
                [
                    24.826799392700195,
                    -11.700200080871582,
                    0.000699999975040555
                ],
                [
                    24.826799392700195,
                    -11.700200080871582,
                    1.9457000494003296
                ],
                [
                    24.826799392700195,
                    11.640800476074219,
                    1.9457000494003296
                ],
                [
                    24.826799392700195,
                    11.640800476074219,
                    0.000699999975040555
                ]
            ],
            "matrix_world": [
                [
                    0.05999999865889549,
                    0.0,
                    0.0,
                    1.5
                ],
                [
                    0.0,
                    0.05999999865889549,
                    0.0,
                    0.4999998211860657
                ],
                [
                    0.0,
                    0.0,
                    0.05999999865889549,
                    4.099999904632568
                ],
                [
                    0.0,
                    0.0,
                    0.0,
                    1.0
                ]
            ],
            "vertex_count": 15553,
            "polygon_count": 16448,
            "material_count": 1
        },
        "laptop1": {
            "name": "laptop1",
            "type": "MESH",
            "visible": true,
            "location": {
                "x": -2.499999523162842,
                "y": 2.0,
                "z": 4.150000095367432
            },
            "rotation_euler": {
                "x": 1.570796251296997,
                "y": 0.0,
                "z": 1.7453292608261108
            },
            "scale": {
                "x": 0.800000011920929,
                "y": 0.800000011920929,
                "z": 0.800000011920929
            },
            "dimensions": {
                "x": 1.831149697303772,
                "y": 1.8746464252471924,
                "z": 2.618126392364502
            },
            "bound_box": [
                [
                    -1.999521017074585,
                    -0.12090999633073807,
                    -1.6349689960479736
                ],
                [
                    -1.999521017074585,
                    -0.12090999633073807,
                    1.6376889944076538
                ],
                [
                    -1.999521017074585,
                    2.222398042678833,
                    1.6376889944076538
                ],
                [
                    -1.999521017074585,
                    2.222398042678833,
                    -1.6349689960479736
                ],
                [
                    0.28941598534584045,
                    -0.12090999633073807,
                    -1.6349689960479736
                ],
                [
                    0.28941598534584045,
                    -0.12090999633073807,
                    1.6376889944076538
                ],
                [
                    0.28941598534584045,
                    2.222398042678833,
                    1.6376889944076538
                ],
                [
                    0.28941598534584045,
                    2.222398042678833,
                    -1.6349689960479736
                ]
            ],
            "matrix_world": [
                [
                    -0.13891856372356415,
                    -5.948073322770142e-08,
                    0.7878462076187134,
                    -2.499999523162842
                ],
                [
                    0.7878462076187134,
                    -1.0488058421742608e-08,
                    0.13891856372356415,
                    2.0
                ],
                [
                    0.0,
                    0.800000011920929,
                    6.039832101123466e-08,
                    4.150000095367432
                ],
                [
                    0.0,
                    0.0,
                    0.0,
                    1.0
                ]
            ],
            "vertex_count": 300,
            "polygon_count": 161,
            "material_count": 2
        },
        "monitor1": {
            "name": "monitor1",
            "type": "MESH",
            "visible": true,
            "location": {
                "x": 1.5,
                "y": 2.0,
                "z": 4.050000190734863
            },
            "rotation_euler": {
                "x": 0.0,
                "y": -0.0,
                "z": 0.0
            },
            "scale": {
                "x": 0.10000000149011612,
                "y": 0.10000000149011612,
                "z": 0.10000000149011612
            },
            "dimensions": {
                "x": 4.390200138092041,
                "y": 1.3304100036621094,
                "z": 3.5898003578186035
            },
            "bound_box": [
                [
                    -21.951000213623047,
                    -3.9382998943328857,
                    -0.013899999670684338
                ],
                [
                    -21.951000213623047,
                    -3.9382998943328857,
                    35.88410186767578
                ],
                [
                    -21.951000213623047,
                    9.365799903869629,
                    35.88410186767578
                ],
                [
                    -21.951000213623047,
                    9.365799903869629,
                    -0.013899999670684338
                ],
                [
                    21.951000213623047,
                    -3.9382998943328857,
                    -0.013899999670684338
                ],
                [
                    21.951000213623047,
                    -3.9382998943328857,
                    35.88410186767578
                ],
                [
                    21.951000213623047,
                    9.365799903869629,
                    35.88410186767578
                ],
                [
                    21.951000213623047,
                    9.365799903869629,
                    -0.013899999670684338
                ]
            ],
            "matrix_world": [
                [
                    0.10000000149011612,
                    0.0,
                    0.0,
                    1.5
                ],
                [
                    0.0,
                    0.10000000149011612,
                    0.0,
                    2.0
                ],
                [
                    0.0,
                    0.0,
                    0.10000000149011612,
                    4.050000190734863
                ],
                [
                    0.0,
                    0.0,
                    0.0,
                    1.0
                ]
            ],
            "vertex_count": 1872,
            "polygon_count": 1864,
            "material_count": 1
        },
        "mouse1": {
            "name": "mouse1",
            "type": "MESH",
            "visible": true,
            "location": {
                "x": 3.5,
                "y": 0.800000011920929,
                "z": 4.050000190734863
            },
            "rotation_euler": {
                "x": 1.570796251296997,
                "y": -0.0,
                "z": 0.0
            },
            "scale": {
                "x": 0.0010000000474974513,
                "y": 0.0010000000474974513,
                "z": 0.0010000000474974513
            },
            "dimensions": {
                "x": 0.5797604322433472,
                "y": 0.22318331897258759,
                "z": 1.1493253707885742
            },
            "bound_box": [
                [
                    -289.8801574707031,
                    -4.76837158203125e-05,
                    -574.6626586914062
                ],
                [
                    -289.8801574707031,
                    -4.76837158203125e-05,
                    574.6626586914062
                ],
                [
                    -289.8801574707031,
                    223.18325805664062,
                    574.6626586914062
                ],
                [
                    -289.8801574707031,
                    223.18325805664062,
                    -574.6626586914062
                ],
                [
                    289.8802185058594,
                    -4.76837158203125e-05,
                    -574.6626586914062
                ],
                [
                    289.8802185058594,
                    -4.76837158203125e-05,
                    574.6626586914062
                ],
                [
                    289.8802185058594,
                    223.18325805664062,
                    574.6626586914062
                ],
                [
                    289.8802185058594,
                    223.18325805664062,
                    -574.6626586914062
                ]
            ],
            "matrix_world": [
                [
                    0.0010000000474974513,
                    0.0,
                    0.0,
                    3.5
                ],
                [
                    0.0,
                    7.549790653760269e-11,
                    -0.0010000000474974513,
                    0.800000011920929
                ],
                [
                    0.0,
                    0.0010000000474974513,
                    7.549790653760269e-11,
                    4.050000190734863
                ],
                [
                    0.0,
                    0.0,
                    0.0,
                    1.0
                ]
            ],
            "vertex_count": 12857,
            "polygon_count": 12133,
            "material_count": 9
        },
        "desk2": {
            "name": "desk2",
            "type": "MESH",
            "visible": true,
            "location": {
                "x": 10.0,
                "y": -4.0,
                "z": 0.0
            },
            "rotation_euler": {
                "x": 1.570796251296997,
                "y": 0.0,
                "z": 0.0
            },
            "scale": {
                "x": 1.0,
                "y": 1.0,
                "z": 1.0
            },
            "dimensions": {
                "x": 4.038548946380615,
                "y": 3.9874911308288574,
                "z": 9.503341674804688
            },
            "bound_box": [
                [
                    -0.47810301184654236,
                    0.05196800082921982,
                    -4.137495994567871
                ],
                [
                    -0.47810301184654236,
                    0.05196800082921982,
                    5.365845203399658
                ],
                [
                    -0.47810301184654236,
                    4.039459228515625,
                    5.365845203399658
                ],
                [
                    -0.47810301184654236,
                    4.039459228515625,
                    -4.137495994567871
                ],
                [
                    3.56044602394104,
                    0.05196800082921982,
                    -4.137495994567871
                ],
                [
                    3.56044602394104,
                    0.05196800082921982,
                    5.365845203399658
                ],
                [
                    3.56044602394104,
                    4.039459228515625,
                    5.365845203399658
                ],
                [
                    3.56044602394104,
                    4.039459228515625,
                    -4.137495994567871
                ]
            ],
            "matrix_world": [
                [
                    1.0,
                    0.0,
                    0.0,
                    10.0
                ],
                [
                    0.0,
                    7.549790126404332e-08,
                    -1.0,
                    -4.0
                ],
                [
                    0.0,
                    1.0,
                    7.549790126404332e-08,
                    0.0
                ],
                [
                    0.0,
                    0.0,
                    0.0,
                    1.0
                ]
            ],
            "vertex_count": 3827,
            "polygon_count": 3716,
            "material_count": 1
        },
        "chair2": {
            "name": "chair2",
            "type": "MESH",
            "visible": true,
            "location": {
                "x": 7.5,
                "y": -4.0,
                "z": 0.0
            },
            "rotation_euler": {
                "x": 1.5707963705062866,
                "y": 0.0,
                "z": 4.71238899230957
            },
            "scale": {
                "x": 0.15000000596046448,
                "y": 0.15000000596046448,
                "z": 0.15000000596046448
            },
            "dimensions": {
                "x": 3.039024829864502,
                "y": 5.048727989196777,
                "z": 3.3212192058563232
            },
            "bound_box": [
                [
                    -10.167875289916992,
                    -0.02954299934208393,
                    -10.566875457763672
                ],
                [
                    -10.167875289916992,
                    -0.02954299934208393,
                    11.5745849609375
                ],
                [
                    -10.167875289916992,
                    33.628639221191406,
                    11.5745849609375
                ],
                [
                    -10.167875289916992,
                    33.628639221191406,
                    -10.566875457763672
                ],
                [
                    10.092288970947266,
                    -0.02954299934208393,
                    -10.566875457763672
                ],
                [
                    10.092288970947266,
                    -0.02954299934208393,
                    11.5745849609375
                ],
                [
                    10.092288970947266,
                    33.628639221191406,
                    11.5745849609375
                ],
                [
                    10.092288970947266,
                    33.628639221191406,
                    -10.566875457763672
                ]
            ],
            "matrix_world": [
                [
                    1.7887321623888397e-09,
                    -6.556708509464215e-09,
                    -0.15000000596046448,
                    7.5
                ],
                [
                    -0.15000000596046448,
                    -7.818797023470916e-17,
                    -1.7887321623888397e-09,
                    -4.0
                ],
                [
                    0.0,
                    0.15000000596046448,
                    -6.556708509464215e-09,
                    0.0
                ],
                [
                    0.0,
                    0.0,
                    0.0,
                    1.0
                ]
            ],
            "vertex_count": 13139,
            "polygon_count": 26104,
            "material_count": 1
        },
        "Light.001": {
            "name": "Light.001",
            "type": "LIGHT",
            "visible": true,
            "location": {
                "x": 9.067132949829102,
                "y": -8.0,
                "z": 6.0
            },
            "rotation_euler": {
                "x": 0.6503279805183411,
                "y": 0.055217113345861435,
                "z": 1.8663908243179321
            },
            "scale": {
                "x": 1.0,
                "y": 1.0,
                "z": 1.0
            },
            "dimensions": {
                "x": 0.0,
                "y": 0.0,
                "z": 0.0
            },
            "bound_box": [
                [
                    0.0,
                    0.0,
                    0.0
                ],
                [
                    0.0,
                    0.0,
                    0.0
                ],
                [
                    0.0,
                    0.0,
                    0.0
                ],
                [
                    0.0,
                    0.0,
                    0.0
                ],
                [
                    0.0,
                    0.0,
                    0.0
                ],
                [
                    0.0,
                    0.0,
                    0.0
                ],
                [
                    0.0,
                    0.0,
                    0.0
                ],
                [
                    0.0,
                    0.0,
                    0.0
                ]
            ],
            "matrix_world": [
                [
                    -0.29086464643478394,
                    -0.7711008191108704,
                    0.5663931965827942,
                    9.067132949829102
                ],
                [
                    0.9551711678504944,
                    -0.1998833566904068,
                    0.21839119493961334,
                    -8.0
                ],
                [
                    -0.05518905818462372,
                    0.6045247316360474,
                    0.7946722507476807,
                    6.0
                ],
                [
                    0.0,
                    0.0,
                    0.0,
                    1.0
                ]
            ]
        },
        "chair3": {
            "name": "chair3",
            "type": "MESH",
            "visible": true,
            "location": {
                "x": 6.0,
                "y": -16.0,
                "z": 0.0
            },
            "rotation_euler": {
                "x": 1.570796251296997,
                "y": 0.0,
                "z": 4.71238899230957
            },
            "scale": {
                "x": 0.15000000596046448,
                "y": 0.15000000596046448,
                "z": 0.15000000596046448
            },
            "dimensions": {
                "x": 3.039024829864502,
                "y": 5.048727989196777,
                "z": 3.3212192058563232
            },
            "bound_box": [
                [
                    -10.167875289916992,
                    -0.02954299934208393,
                    -10.566875457763672
                ],
                [
                    -10.167875289916992,
                    -0.02954299934208393,
                    11.5745849609375
                ],
                [
                    -10.167875289916992,
                    33.628639221191406,
                    11.5745849609375
                ],
                [
                    -10.167875289916992,
                    33.628639221191406,
                    -10.566875457763672
                ],
                [
                    10.092288970947266,
                    -0.02954299934208393,
                    -10.566875457763672
                ],
                [
                    10.092288970947266,
                    -0.02954299934208393,
                    11.5745849609375
                ],
                [
                    10.092288970947266,
                    33.628639221191406,
                    11.5745849609375
                ],
                [
                    10.092288970947266,
                    33.628639221191406,
                    -10.566875457763672
                ]
            ],
            "matrix_world": [
                [
                    1.7887321623888397e-09,
                    1.1324686077784918e-08,
                    -0.15000000596046448,
                    6.0
                ],
                [
                    -0.15000000596046448,
                    1.350455068054073e-16,
                    -1.7887321623888397e-09,
                    -16.0
                ],
                [
                    0.0,
                    0.15000000596046448,
                    1.1324686077784918e-08,
                    0.0
                ],
                [
                    0.0,
                    0.0,
                    0.0,
                    1.0
                ]
            ],
            "vertex_count": 13139,
            "polygon_count": 26104,
            "material_count": 1
        },
        "desk3": {
            "name": "desk3",
            "type": "MESH",
            "visible": true,
            "location": {
                "x": 10.0,
                "y": -16.0,
                "z": 0.0
            },
            "rotation_euler": {
                "x": 1.570796251296997,
                "y": 0.0,
                "z": 0.0
            },
            "scale": {
                "x": 1.0,
                "y": 1.0,
                "z": 1.0
            },
            "dimensions": {
                "x": 4.038548946380615,
                "y": 3.9874911308288574,
                "z": 9.503341674804688
            },
            "bound_box": [
                [
                    -0.47810301184654236,
                    0.05196800082921982,
                    -4.137495994567871
                ],
                [
                    -0.47810301184654236,
                    0.05196800082921982,
                    5.365845203399658
                ],
                [
                    -0.47810301184654236,
                    4.039459228515625,
                    5.365845203399658
                ],
                [
                    -0.47810301184654236,
                    4.039459228515625,
                    -4.137495994567871
                ],
                [
                    3.56044602394104,
                    0.05196800082921982,
                    -4.137495994567871
                ],
                [
                    3.56044602394104,
                    0.05196800082921982,
                    5.365845203399658
                ],
                [
                    3.56044602394104,
                    4.039459228515625,
                    5.365845203399658
                ],
                [
                    3.56044602394104,
                    4.039459228515625,
                    -4.137495994567871
                ]
            ],
            "matrix_world": [
                [
                    1.0,
                    0.0,
                    0.0,
                    10.0
                ],
                [
                    0.0,
                    7.549790126404332e-08,
                    -1.0,
                    -16.0
                ],
                [
                    0.0,
                    1.0,
                    7.549790126404332e-08,
                    0.0
                ],
                [
                    0.0,
                    0.0,
                    0.0,
                    1.0
                ]
            ],
            "vertex_count": 3827,
            "polygon_count": 3716,
            "material_count": 1
        },
        "keyboard2": {
            "name": "keyboard2",
            "type": "MESH",
            "visible": true,
            "location": {
                "x": 11.0,
                "y": -17.0,
                "z": 4.099999904632568
            },
            "rotation_euler": {
                "x": 0.0,
                "y": -0.0,
                "z": 1.5707963705062866
            },
            "scale": {
                "x": 0.05999999865889549,
                "y": 0.05999999865889549,
                "z": 0.05999999865889549
            },
            "dimensions": {
                "x": 2.9757118225097656,
                "y": 1.400459885597229,
                "z": 0.11670000106096268
            },
            "bound_box": [
                [
                    -24.768400192260742,
                    -11.700200080871582,
                    0.000699999975040555
                ],
                [
                    -24.768400192260742,
                    -11.700200080871582,
                    1.9457000494003296
                ],
                [
                    -24.768400192260742,
                    11.640800476074219,
                    1.9457000494003296
                ],
                [
                    -24.768400192260742,
                    11.640800476074219,
                    0.000699999975040555
                ],
                [
                    24.826799392700195,
                    -11.700200080871582,
                    0.000699999975040555
                ],
                [
                    24.826799392700195,
                    -11.700200080871582,
                    1.9457000494003296
                ],
                [
                    24.826799392700195,
                    11.640800476074219,
                    1.9457000494003296
                ],
                [
                    24.826799392700195,
                    11.640800476074219,
                    0.000699999975040555
                ]
            ],
            "matrix_world": [
                [
                    -2.622683181741081e-09,
                    -0.05999999865889549,
                    0.0,
                    11.0
                ],
                [
                    0.05999999865889549,
                    -2.622683181741081e-09,
                    0.0,
                    -17.0
                ],
                [
                    0.0,
                    0.0,
                    0.05999999865889549,
                    4.099999904632568
                ],
                [
                    0.0,
                    0.0,
                    0.0,
                    1.0
                ]
            ],
            "vertex_count": 15553,
            "polygon_count": 16448,
            "material_count": 1
        },
        "monitor2": {
            "name": "monitor2",
            "type": "MESH",
            "visible": true,
            "location": {
                "x": 12.5,
                "y": -17.0,
                "z": 4.050000190734863
            },
            "rotation_euler": {
                "x": 0.0,
                "y": -0.0,
                "z": -1.5707963705062866
            },
            "scale": {
                "x": 0.10000000149011612,
                "y": 0.10000000149011612,
                "z": 0.10000000149011612
            },
            "dimensions": {
                "x": 4.390200138092041,
                "y": 1.3304100036621094,
                "z": 3.5898003578186035
            },
            "bound_box": [
                [
                    -21.951000213623047,
                    -3.9382998943328857,
                    -0.013899999670684338
                ],
                [
                    -21.951000213623047,
                    -3.9382998943328857,
                    35.88410186767578
                ],
                [
                    -21.951000213623047,
                    9.365799903869629,
                    35.88410186767578
                ],
                [
                    -21.951000213623047,
                    9.365799903869629,
                    -0.013899999670684338
                ],
                [
                    21.951000213623047,
                    -3.9382998943328857,
                    -0.013899999670684338
                ],
                [
                    21.951000213623047,
                    -3.9382998943328857,
                    35.88410186767578
                ],
                [
                    21.951000213623047,
                    9.365799903869629,
                    35.88410186767578
                ],
                [
                    21.951000213623047,
                    9.365799903869629,
                    -0.013899999670684338
                ]
            ],
            "matrix_world": [
                [
                    -4.371139006309477e-09,
                    0.10000000149011612,
                    0.0,
                    12.5
                ],
                [
                    -0.10000000149011612,
                    -4.371139006309477e-09,
                    0.0,
                    -17.0
                ],
                [
                    0.0,
                    0.0,
                    0.10000000149011612,
                    4.050000190734863
                ],
                [
                    0.0,
                    0.0,
                    0.0,
                    1.0
                ]
            ],
            "vertex_count": 1872,
            "polygon_count": 1864,
            "material_count": 1
        },
        "mouse2": {
            "name": "mouse2",
            "type": "MESH",
            "visible": true,
            "location": {
                "x": 11.0,
                "y": -19.0,
                "z": 4.050000190734863
            },
            "rotation_euler": {
                "x": 1.570796251296997,
                "y": -0.0,
                "z": 1.5707963705062866
            },
            "scale": {
                "x": 0.0010000000474974513,
                "y": 0.0010000000474974513,
                "z": 0.0010000000474974513
            },
            "dimensions": {
                "x": 0.5797604322433472,
                "y": 0.22318331897258759,
                "z": 1.1493253707885742
            },
            "bound_box": [
                [
                    -289.8801574707031,
                    -4.76837158203125e-05,
                    -574.6626586914062
                ],
                [
                    -289.8801574707031,
                    -4.76837158203125e-05,
                    574.6626586914062
                ],
                [
                    -289.8801574707031,
                    223.18325805664062,
                    574.6626586914062
                ],
                [
                    -289.8801574707031,
                    223.18325805664062,
                    -574.6626586914062
                ],
                [
                    289.8802185058594,
                    -4.76837158203125e-05,
                    -574.6626586914062
                ],
                [
                    289.8802185058594,
                    -4.76837158203125e-05,
                    574.6626586914062
                ],
                [
                    289.8802185058594,
                    223.18325805664062,
                    574.6626586914062
                ],
                [
                    289.8802185058594,
                    223.18325805664062,
                    -574.6626586914062
                ]
            ],
            "matrix_world": [
                [
                    -4.371138867531599e-11,
                    -7.549790653760269e-11,
                    0.0010000000474974513,
                    11.0
                ],
                [
                    0.0010000000474974513,
                    -3.3001183242754872e-18,
                    4.371138867531599e-11,
                    -19.0
                ],
                [
                    0.0,
                    0.0010000000474974513,
                    7.549790653760269e-11,
                    4.050000190734863
                ],
                [
                    0.0,
                    0.0,
                    0.0,
                    1.0
                ]
            ],
            "vertex_count": 12857,
            "polygon_count": 12133,
            "material_count": 9
        }
    }
}